{
  "activity_name": "com.zonewalker.acar/com.zonewalker.acar.view.core.AboutActivity", 
  "activity": {
    "root": {
      "scrollable-horizontal": false, 
      "draw": true, 
      "ancestors": [
        "android.widget.FrameLayout", 
        "android.view.ViewGroup", 
        "android.view.View", 
        "java.lang.Object"
      ], 
      "clickable": false, 
      "pressed": "not_pressed", 
      "focusable": false, 
      "long-clickable": false, 
      "enabled": true, 
      "bounds": [
        0, 
        0, 
        1440, 
        2392
      ], 
      "visibility": "visible", 
      "content-desc": [
        null
      ], 
      "rel-bounds": [
        0, 
        0, 
        1440, 
        2392
      ], 
      "focused": false, 
      "selected": false, 
      "scrollable-vertical": false, 
      "children": [
        {
          "scrollable-horizontal": false, 
          "draw": true, 
          "ancestors": [
            "android.view.ViewGroup", 
            "android.view.View", 
            "java.lang.Object"
          ], 
          "clickable": false, 
          "pressed": "not_pressed", 
          "focusable": false, 
          "long-clickable": false, 
          "enabled": true, 
          "bounds": [
            0, 
            0, 
            1440, 
            2392
          ], 
          "visibility": "visible", 
          "content-desc": [
            null
          ], 
          "rel-bounds": [
            0, 
            0, 
            1440, 
            2392
          ], 
          "focused": false, 
          "selected": false, 
          "scrollable-vertical": false, 
          "children": [
            {
              "resource-id": "android:id/action_mode_bar_stub", 
              "adapter-view": false, 
              "pointer": "a86eb44", 
              "scrollable-horizontal": false, 
              "ancestors": [
                "android.view.View", 
                "java.lang.Object"
              ], 
              "selected": false, 
              "content-desc": [
                null
              ], 
              "rel-bounds": [
                0, 
                0, 
                0, 
                0
              ], 
              "draw": true, 
              "focusable": false, 
              "long-clickable": false, 
              "visibility": "gone", 
              "focused": false, 
              "clickable": false, 
              "abs-pos": true, 
              "class": "android.view.ViewStub", 
              "visible-to-user": false, 
              "package": "android", 
              "enabled": true, 
              "bounds": [
                0, 
                0, 
                0, 
                0
              ], 
              "pressed": "not_pressed", 
              "scrollable-vertical": false
            }, 
            {
              "resource-id": "android:id/title_container", 
              "adapter-view": false, 
              "pointer": "1b9142d", 
              "children": [
                {
                  "scrollable-horizontal": false, 
                  "draw": true, 
                  "ancestors": [
                    "android.view.ViewGroup", 
                    "android.view.View", 
                    "java.lang.Object"
                  ], 
                  "clickable": false, 
                  "pressed": "not_pressed", 
                  "focusable": false, 
                  "long-clickable": false, 
                  "enabled": true, 
                  "bounds": [
                    0, 
                    84, 
                    1440, 
                    231
                  ], 
                  "visibility": "visible", 
                  "content-desc": [
                    null
                  ], 
                  "rel-bounds": [
                    0, 
                    0, 
                    1440, 
                    147
                  ], 
                  "focused": false, 
                  "selected": false, 
                  "scrollable-vertical": false, 
                  "children": [
                    {
                      "resource-id": "com.zonewalker.acar:id/img_icon", 
                      "adapter-view": false, 
                      "pointer": "d626ef3", 
                      "scrollable-horizontal": false, 
                      "ancestors": [
                        "android.view.View", 
                        "java.lang.Object"
                      ], 
                      "selected": false, 
                      "content-desc": [
                        null
                      ], 
                      "rel-bounds": [
                        18, 
                        18, 
                        158, 
                        129
                      ], 
                      "draw": false, 
                      "focusable": false, 
                      "long-clickable": false, 
                      "visibility": "visible", 
                      "focused": false, 
                      "clickable": true, 
                      "abs-pos": true, 
                      "class": "android.widget.ImageView", 
                      "visible-to-user": true, 
                      "package": "com.zonewalker.acar", 
                      "enabled": true, 
                      "bounds": [
                        18, 
                        102, 
                        158, 
                        213
                      ], 
                      "pressed": "not_pressed", 
                      "scrollable-vertical": false
                    }, 
                    {
                      "scrollable-horizontal": false, 
                      "draw": true, 
                      "ancestors": [
                        "android.view.ViewGroup", 
                        "android.view.View", 
                        "java.lang.Object"
                      ], 
                      "clickable": false, 
                      "pressed": "not_pressed", 
                      "focusable": false, 
                      "long-clickable": false, 
                      "enabled": true, 
                      "bounds": [
                        158, 
                        102, 
                        1282, 
                        213
                      ], 
                      "visibility": "visible", 
                      "content-desc": [
                        null
                      ], 
                      "rel-bounds": [
                        158, 
                        18, 
                        1282, 
                        129
                      ], 
                      "focused": false, 
                      "selected": false, 
                      "scrollable-vertical": false, 
                      "children": [
                        {
                          "scrollable-horizontal": false, 
                          "draw": true, 
                          "ancestors": [
                            "android.view.ViewGroup", 
                            "android.view.View", 
                            "java.lang.Object"
                          ], 
                          "clickable": false, 
                          "pressed": "not_pressed", 
                          "focusable": false, 
                          "long-clickable": false, 
                          "enabled": true, 
                          "bounds": [
                            158, 
                            102, 
                            1282, 
                            213
                          ], 
                          "visibility": "visible", 
                          "content-desc": [
                            null
                          ], 
                          "rel-bounds": [
                            0, 
                            0, 
                            1124, 
                            111
                          ], 
                          "focused": false, 
                          "selected": false, 
                          "scrollable-vertical": false, 
                          "children": [
                            {
                              "resource-id": "com.zonewalker.acar:id/layout_context1", 
                              "adapter-view": false, 
                              "pointer": "3be0dae", 
                              "children": [
                                {
                                  "resource-id": "com.zonewalker.acar:id/img_context1_switcher_left", 
                                  "adapter-view": false, 
                                  "pointer": "2ab074f", 
                                  "scrollable-horizontal": false, 
                                  "ancestors": [
                                    "android.view.View", 
                                    "java.lang.Object"
                                  ], 
                                  "selected": false, 
                                  "content-desc": [
                                    null
                                  ], 
                                  "rel-bounds": [
                                    0, 
                                    0, 
                                    0, 
                                    0
                                  ], 
                                  "draw": false, 
                                  "focusable": false, 
                                  "long-clickable": false, 
                                  "visibility": "gone", 
                                  "focused": false, 
                                  "clickable": false, 
                                  "abs-pos": true, 
                                  "class": "android.widget.ImageView", 
                                  "visible-to-user": false, 
                                  "package": "com.zonewalker.acar", 
                                  "enabled": true, 
                                  "bounds": [
                                    158, 
                                    102, 
                                    158, 
                                    102
                                  ], 
                                  "pressed": "not_pressed", 
                                  "scrollable-vertical": false
                                }, 
                                {
                                  "text": "About aCar . . .", 
                                  "resource-id": "com.zonewalker.acar:id/txt_context1", 
                                  "adapter-view": false, 
                                  "pointer": "5265edc", 
                                  "scrollable-horizontal": false, 
                                  "ancestors": [
                                    "android.view.View", 
                                    "java.lang.Object"
                                  ], 
                                  "selected": false, 
                                  "content-desc": [
                                    null
                                  ], 
                                  "rel-bounds": [
                                    348, 
                                    0, 
                                    775, 
                                    111
                                  ], 
                                  "draw": false, 
                                  "focusable": false, 
                                  "long-clickable": false, 
                                  "visibility": "visible", 
                                  "focused": false, 
                                  "clickable": false, 
                                  "abs-pos": true, 
                                  "class": "android.widget.TextView", 
                                  "visible-to-user": true, 
                                  "package": "com.zonewalker.acar", 
                                  "enabled": true, 
                                  "bounds": [
                                    506, 
                                    102, 
                                    933, 
                                    213
                                  ], 
                                  "pressed": "not_pressed", 
                                  "scrollable-vertical": false
                                }, 
                                {
                                  "resource-id": "com.zonewalker.acar:id/img_context1_switcher_right", 
                                  "adapter-view": false, 
                                  "pointer": "c659be5", 
                                  "scrollable-horizontal": false, 
                                  "ancestors": [
                                    "android.view.View", 
                                    "java.lang.Object"
                                  ], 
                                  "selected": false, 
                                  "content-desc": [
                                    null
                                  ], 
                                  "rel-bounds": [
                                    0, 
                                    0, 
                                    0, 
                                    0
                                  ], 
                                  "draw": false, 
                                  "focusable": false, 
                                  "long-clickable": false, 
                                  "visibility": "gone", 
                                  "focused": false, 
                                  "clickable": false, 
                                  "abs-pos": true, 
                                  "class": "android.widget.ImageView", 
                                  "visible-to-user": false, 
                                  "package": "com.zonewalker.acar", 
                                  "enabled": true, 
                                  "bounds": [
                                    158, 
                                    102, 
                                    158, 
                                    102
                                  ], 
                                  "pressed": "not_pressed", 
                                  "scrollable-vertical": false
                                }
                              ], 
                              "scrollable-horizontal": false, 
                              "ancestors": [
                                "android.view.ViewGroup", 
                                "android.view.View", 
                                "java.lang.Object"
                              ], 
                              "selected": false, 
                              "content-desc": [
                                null
                              ], 
                              "rel-bounds": [
                                0, 
                                0, 
                                1124, 
                                111
                              ], 
                              "draw": true, 
                              "focusable": false, 
                              "long-clickable": false, 
                              "visibility": "visible", 
                              "focused": false, 
                              "clickable": false, 
                              "abs-pos": true, 
                              "class": "android.widget.LinearLayout", 
                              "visible-to-user": true, 
                              "package": "com.zonewalker.acar", 
                              "enabled": true, 
                              "bounds": [
                                158, 
                                102, 
                                1282, 
                                213
                              ], 
                              "pressed": "not_pressed", 
                              "scrollable-vertical": false
                            }, 
                            {
                              "resource-id": "com.zonewalker.acar:id/layout_context2", 
                              "adapter-view": false, 
                              "pointer": "4e156ba", 
                              "children": [
                                {
                                  "resource-id": "com.zonewalker.acar:id/img_context2_switcher_left", 
                                  "adapter-view": false, 
                                  "pointer": "a3ac96b", 
                                  "scrollable-horizontal": false, 
                                  "ancestors": [
                                    "android.view.View", 
                                    "java.lang.Object"
                                  ], 
                                  "selected": false, 
                                  "content-desc": [
                                    null
                                  ], 
                                  "rel-bounds": [
                                    0, 
                                    0, 
                                    0, 
                                    0
                                  ], 
                                  "draw": false, 
                                  "focusable": false, 
                                  "long-clickable": false, 
                                  "visibility": "gone", 
                                  "focused": false, 
                                  "clickable": false, 
                                  "abs-pos": true, 
                                  "class": "android.widget.ImageView", 
                                  "visible-to-user": false, 
                                  "package": "com.zonewalker.acar", 
                                  "enabled": true, 
                                  "bounds": [
                                    158, 
                                    102, 
                                    158, 
                                    102
                                  ], 
                                  "pressed": "not_pressed", 
                                  "scrollable-vertical": false
                                }, 
                                {
                                  "text": "", 
                                  "resource-id": "com.zonewalker.acar:id/txt_context2", 
                                  "adapter-view": false, 
                                  "pointer": "8288cc8", 
                                  "scrollable-horizontal": false, 
                                  "ancestors": [
                                    "android.view.View", 
                                    "java.lang.Object"
                                  ], 
                                  "selected": false, 
                                  "content-desc": [
                                    null
                                  ], 
                                  "rel-bounds": [
                                    0, 
                                    0, 
                                    0, 
                                    0
                                  ], 
                                  "draw": false, 
                                  "focusable": false, 
                                  "long-clickable": false, 
                                  "visibility": "visible", 
                                  "focused": false, 
                                  "clickable": false, 
                                  "abs-pos": true, 
                                  "class": "android.widget.TextView", 
                                  "visible-to-user": false, 
                                  "package": "com.zonewalker.acar", 
                                  "enabled": true, 
                                  "bounds": [
                                    158, 
                                    102, 
                                    158, 
                                    102
                                  ], 
                                  "pressed": "not_pressed", 
                                  "scrollable-vertical": false
                                }, 
                                {
                                  "resource-id": "com.zonewalker.acar:id/img_context2_switcher_right", 
                                  "adapter-view": false, 
                                  "pointer": "ed91161", 
                                  "scrollable-horizontal": false, 
                                  "ancestors": [
                                    "android.view.View", 
                                    "java.lang.Object"
                                  ], 
                                  "selected": false, 
                                  "content-desc": [
                                    null
                                  ], 
                                  "rel-bounds": [
                                    0, 
                                    0, 
                                    0, 
                                    0
                                  ], 
                                  "draw": false, 
                                  "focusable": false, 
                                  "long-clickable": false, 
                                  "visibility": "gone", 
                                  "focused": false, 
                                  "clickable": false, 
                                  "abs-pos": true, 
                                  "class": "android.widget.ImageView", 
                                  "visible-to-user": false, 
                                  "package": "com.zonewalker.acar", 
                                  "enabled": true, 
                                  "bounds": [
                                    158, 
                                    102, 
                                    158, 
                                    102
                                  ], 
                                  "pressed": "not_pressed", 
                                  "scrollable-vertical": false
                                }
                              ], 
                              "scrollable-horizontal": false, 
                              "ancestors": [
                                "android.view.ViewGroup", 
                                "android.view.View", 
                                "java.lang.Object"
                              ], 
                              "selected": false, 
                              "content-desc": [
                                null
                              ], 
                              "rel-bounds": [
                                0, 
                                0, 
                                0, 
                                0
                              ], 
                              "draw": true, 
                              "focusable": false, 
                              "long-clickable": false, 
                              "visibility": "gone", 
                              "focused": false, 
                              "clickable": false, 
                              "abs-pos": true, 
                              "class": "android.widget.LinearLayout", 
                              "visible-to-user": false, 
                              "package": "com.zonewalker.acar", 
                              "enabled": true, 
                              "bounds": [
                                158, 
                                102, 
                                158, 
                                102
                              ], 
                              "pressed": "not_pressed", 
                              "scrollable-vertical": false
                            }, 
                            {
                              "resource-id": "com.zonewalker.acar:id/layout_context3", 
                              "adapter-view": false, 
                              "pointer": "7be2486", 
                              "children": [
                                {
                                  "resource-id": "com.zonewalker.acar:id/img_context3_switcher_left", 
                                  "adapter-view": false, 
                                  "pointer": "ba9147", 
                                  "scrollable-horizontal": false, 
                                  "ancestors": [
                                    "android.view.View", 
                                    "java.lang.Object"
                                  ], 
                                  "selected": false, 
                                  "content-desc": [
                                    null
                                  ], 
                                  "rel-bounds": [
                                    0, 
                                    0, 
                                    0, 
                                    0
                                  ], 
                                  "draw": false, 
                                  "focusable": false, 
                                  "long-clickable": false, 
                                  "visibility": "gone", 
                                  "focused": false, 
                                  "clickable": false, 
                                  "abs-pos": true, 
                                  "class": "android.widget.ImageView", 
                                  "visible-to-user": false, 
                                  "package": "com.zonewalker.acar", 
                                  "enabled": true, 
                                  "bounds": [
                                    158, 
                                    102, 
                                    158, 
                                    102
                                  ], 
                                  "pressed": "not_pressed", 
                                  "scrollable-vertical": false
                                }, 
                                {
                                  "text": "", 
                                  "resource-id": "com.zonewalker.acar:id/txt_context3", 
                                  "adapter-view": false, 
                                  "pointer": "b9dad74", 
                                  "scrollable-horizontal": false, 
                                  "ancestors": [
                                    "android.view.View", 
                                    "java.lang.Object"
                                  ], 
                                  "selected": false, 
                                  "content-desc": [
                                    null
                                  ], 
                                  "rel-bounds": [
                                    0, 
                                    0, 
                                    0, 
                                    0
                                  ], 
                                  "draw": false, 
                                  "focusable": false, 
                                  "long-clickable": false, 
                                  "visibility": "visible", 
                                  "focused": false, 
                                  "clickable": false, 
                                  "abs-pos": true, 
                                  "class": "android.widget.TextView", 
                                  "visible-to-user": false, 
                                  "package": "com.zonewalker.acar", 
                                  "enabled": true, 
                                  "bounds": [
                                    158, 
                                    102, 
                                    158, 
                                    102
                                  ], 
                                  "pressed": "not_pressed", 
                                  "scrollable-vertical": false
                                }, 
                                {
                                  "resource-id": "com.zonewalker.acar:id/img_context3_switcher_right", 
                                  "adapter-view": false, 
                                  "pointer": "8b4629d", 
                                  "scrollable-horizontal": false, 
                                  "ancestors": [
                                    "android.view.View", 
                                    "java.lang.Object"
                                  ], 
                                  "selected": false, 
                                  "content-desc": [
                                    null
                                  ], 
                                  "rel-bounds": [
                                    0, 
                                    0, 
                                    0, 
                                    0
                                  ], 
                                  "draw": false, 
                                  "focusable": false, 
                                  "long-clickable": false, 
                                  "visibility": "gone", 
                                  "focused": false, 
                                  "clickable": false, 
                                  "abs-pos": true, 
                                  "class": "android.widget.ImageView", 
                                  "visible-to-user": false, 
                                  "package": "com.zonewalker.acar", 
                                  "enabled": true, 
                                  "bounds": [
                                    158, 
                                    102, 
                                    158, 
                                    102
                                  ], 
                                  "pressed": "not_pressed", 
                                  "scrollable-vertical": false
                                }
                              ], 
                              "scrollable-horizontal": false, 
                              "ancestors": [
                                "android.view.ViewGroup", 
                                "android.view.View", 
                                "java.lang.Object"
                              ], 
                              "selected": false, 
                              "content-desc": [
                                null
                              ], 
                              "rel-bounds": [
                                0, 
                                0, 
                                0, 
                                0
                              ], 
                              "draw": true, 
                              "focusable": false, 
                              "long-clickable": false, 
                              "visibility": "gone", 
                              "focused": false, 
                              "clickable": false, 
                              "abs-pos": true, 
                              "class": "android.widget.LinearLayout", 
                              "visible-to-user": false, 
                              "package": "com.zonewalker.acar", 
                              "enabled": true, 
                              "bounds": [
                                158, 
                                102, 
                                158, 
                                102
                              ], 
                              "pressed": "not_pressed", 
                              "scrollable-vertical": false
                            }
                          ], 
                          "adapter-view": false, 
                          "abs-pos": true, 
                          "pointer": "3bfc629", 
                          "class": "android.widget.LinearLayout", 
                          "visible-to-user": true
                        }, 
                        {
                          "resource-id": "com.zonewalker.acar:id/img_loading_wait", 
                          "adapter-view": false, 
                          "pointer": "d480312", 
                          "scrollable-horizontal": false, 
                          "ancestors": [
                            "android.view.View", 
                            "java.lang.Object"
                          ], 
                          "selected": false, 
                          "content-desc": [
                            null
                          ], 
                          "rel-bounds": [
                            0, 
                            0, 
                            0, 
                            0
                          ], 
                          "draw": false, 
                          "focusable": false, 
                          "long-clickable": false, 
                          "visibility": "gone", 
                          "focused": false, 
                          "clickable": false, 
                          "abs-pos": true, 
                          "class": "android.widget.ImageView", 
                          "visible-to-user": false, 
                          "package": "com.zonewalker.acar", 
                          "enabled": true, 
                          "bounds": [
                            158, 
                            102, 
                            158, 
                            102
                          ], 
                          "pressed": "not_pressed", 
                          "scrollable-vertical": false
                        }
                      ], 
                      "adapter-view": false, 
                      "abs-pos": true, 
                      "pointer": "3a977b0", 
                      "class": "android.widget.RelativeLayout", 
                      "visible-to-user": true
                    }, 
                    {
                      "scrollable-horizontal": false, 
                      "draw": true, 
                      "ancestors": [
                        "android.view.ViewGroup", 
                        "android.view.View", 
                        "java.lang.Object"
                      ], 
                      "clickable": false, 
                      "pressed": "not_pressed", 
                      "focusable": false, 
                      "long-clickable": false, 
                      "enabled": true, 
                      "bounds": [
                        1282, 
                        102, 
                        1422, 
                        213
                      ], 
                      "visibility": "visible", 
                      "content-desc": [
                        null
                      ], 
                      "rel-bounds": [
                        1282, 
                        18, 
                        1422, 
                        129
                      ], 
                      "focused": false, 
                      "selected": false, 
                      "scrollable-vertical": false, 
                      "children": [
                        {
                          "resource-id": "com.zonewalker.acar:id/btn_action1", 
                          "adapter-view": false, 
                          "pointer": "da22ce0", 
                          "scrollable-horizontal": false, 
                          "ancestors": [
                            "android.view.View", 
                            "java.lang.Object"
                          ], 
                          "selected": false, 
                          "content-desc": [
                            null
                          ], 
                          "rel-bounds": [
                            0, 
                            0, 
                            0, 
                            0
                          ], 
                          "draw": false, 
                          "focusable": false, 
                          "long-clickable": false, 
                          "visibility": "gone", 
                          "focused": false, 
                          "clickable": false, 
                          "abs-pos": true, 
                          "class": "android.widget.ImageView", 
                          "visible-to-user": false, 
                          "package": "com.zonewalker.acar", 
                          "enabled": true, 
                          "bounds": [
                            1282, 
                            102, 
                            1282, 
                            102
                          ], 
                          "pressed": "not_pressed", 
                          "scrollable-vertical": false
                        }, 
                        {
                          "resource-id": "com.zonewalker.acar:id/btn_action2", 
                          "adapter-view": false, 
                          "pointer": "cf98b99", 
                          "scrollable-horizontal": false, 
                          "ancestors": [
                            "android.view.View", 
                            "java.lang.Object"
                          ], 
                          "selected": false, 
                          "content-desc": [
                            null
                          ], 
                          "rel-bounds": [
                            0, 
                            0, 
                            0, 
                            0
                          ], 
                          "draw": false, 
                          "focusable": false, 
                          "long-clickable": false, 
                          "visibility": "gone", 
                          "focused": false, 
                          "clickable": false, 
                          "abs-pos": true, 
                          "class": "android.widget.ImageView", 
                          "visible-to-user": false, 
                          "package": "com.zonewalker.acar", 
                          "enabled": true, 
                          "bounds": [
                            1282, 
                            102, 
                            1282, 
                            102
                          ], 
                          "pressed": "not_pressed", 
                          "scrollable-vertical": false
                        }, 
                        {
                          "resource-id": "com.zonewalker.acar:id/btn_action3", 
                          "adapter-view": false, 
                          "pointer": "1f3e5e", 
                          "scrollable-horizontal": false, 
                          "ancestors": [
                            "android.view.View", 
                            "java.lang.Object"
                          ], 
                          "selected": false, 
                          "content-desc": [
                            null
                          ], 
                          "rel-bounds": [
                            0, 
                            0, 
                            0, 
                            0
                          ], 
                          "draw": false, 
                          "focusable": false, 
                          "long-clickable": false, 
                          "visibility": "gone", 
                          "focused": false, 
                          "clickable": false, 
                          "abs-pos": true, 
                          "class": "android.widget.ImageView", 
                          "visible-to-user": false, 
                          "package": "com.zonewalker.acar", 
                          "enabled": true, 
                          "bounds": [
                            1282, 
                            102, 
                            1282, 
                            102
                          ], 
                          "pressed": "not_pressed", 
                          "scrollable-vertical": false
                        }, 
                        {
                          "resource-id": "com.zonewalker.acar:id/btn_action_overflow", 
                          "adapter-view": false, 
                          "pointer": "d02623f", 
                          "scrollable-horizontal": false, 
                          "ancestors": [
                            "android.view.View", 
                            "java.lang.Object"
                          ], 
                          "selected": false, 
                          "content-desc": [
                            null
                          ], 
                          "rel-bounds": [
                            0, 
                            0, 
                            140, 
                            111
                          ], 
                          "draw": false, 
                          "focusable": false, 
                          "long-clickable": false, 
                          "visibility": "visible", 
                          "focused": false, 
                          "clickable": true, 
                          "abs-pos": true, 
                          "class": "android.widget.ImageView", 
                          "visible-to-user": true, 
                          "package": "com.zonewalker.acar", 
                          "enabled": true, 
                          "bounds": [
                            1282, 
                            102, 
                            1422, 
                            213
                          ], 
                          "pressed": "not_pressed", 
                          "scrollable-vertical": false
                        }
                      ], 
                      "adapter-view": false, 
                      "abs-pos": true, 
                      "pointer": "a84fae3", 
                      "class": "android.widget.LinearLayout", 
                      "visible-to-user": true
                    }
                  ], 
                  "adapter-view": false, 
                  "abs-pos": true, 
                  "pointer": "7c17d62", 
                  "class": "android.widget.LinearLayout", 
                  "visible-to-user": true
                }
              ], 
              "scrollable-horizontal": false, 
              "ancestors": [
                "android.view.ViewGroup", 
                "android.view.View", 
                "java.lang.Object"
              ], 
              "selected": false, 
              "content-desc": [
                null
              ], 
              "rel-bounds": [
                0, 
                84, 
                1440, 
                231
              ], 
              "draw": true, 
              "focusable": false, 
              "long-clickable": false, 
              "visibility": "visible", 
              "focused": false, 
              "clickable": false, 
              "abs-pos": true, 
              "class": "android.widget.FrameLayout", 
              "visible-to-user": true, 
              "package": "android", 
              "enabled": true, 
              "bounds": [
                0, 
                84, 
                1440, 
                231
              ], 
              "pressed": "not_pressed", 
              "scrollable-vertical": false
            }, 
            {
              "resource-id": "android:id/content", 
              "adapter-view": false, 
              "pointer": "fad370c", 
              "children": [
                {
                  "scrollable-horizontal": false, 
                  "draw": false, 
                  "ancestors": [
                    "android.widget.FrameLayout", 
                    "android.view.ViewGroup", 
                    "android.view.View", 
                    "java.lang.Object"
                  ], 
                  "clickable": false, 
                  "pressed": "not_pressed", 
                  "focusable": true, 
                  "long-clickable": false, 
                  "enabled": true, 
                  "bounds": [
                    0, 
                    231, 
                    1440, 
                    2392
                  ], 
                  "visibility": "visible", 
                  "content-desc": [
                    null
                  ], 
                  "rel-bounds": [
                    0, 
                    0, 
                    1440, 
                    2161
                  ], 
                  "focused": false, 
                  "selected": false, 
                  "scrollable-vertical": true, 
                  "children": [
                    {
                      "scrollable-horizontal": false, 
                      "draw": true, 
                      "ancestors": [
                        "android.view.ViewGroup", 
                        "android.view.View", 
                        "java.lang.Object"
                      ], 
                      "clickable": false, 
                      "pressed": "not_pressed", 
                      "focusable": false, 
                      "long-clickable": false, 
                      "enabled": true, 
                      "bounds": [
                        0, 
                        231, 
                        1440, 
                        2124
                      ], 
                      "visibility": "visible", 
                      "content-desc": [
                        null
                      ], 
                      "rel-bounds": [
                        0, 
                        0, 
                        1440, 
                        1893
                      ], 
                      "focused": false, 
                      "selected": false, 
                      "scrollable-vertical": false, 
                      "children": [
                        {
                          "scrollable-horizontal": false, 
                          "draw": true, 
                          "ancestors": [
                            "android.view.ViewGroup", 
                            "android.view.View", 
                            "java.lang.Object"
                          ], 
                          "clickable": false, 
                          "pressed": "not_pressed", 
                          "focusable": false, 
                          "long-clickable": false, 
                          "enabled": true, 
                          "bounds": [
                            378, 
                            256, 
                            1062, 
                            332
                          ], 
                          "visibility": "visible", 
                          "content-desc": [
                            null
                          ], 
                          "rel-bounds": [
                            378, 
                            25, 
                            1062, 
                            101
                          ], 
                          "focused": false, 
                          "selected": false, 
                          "scrollable-vertical": false, 
                          "children": [
                            {
                              "scrollable-horizontal": false, 
                              "draw": false, 
                              "ancestors": [
                                "android.view.View", 
                                "java.lang.Object"
                              ], 
                              "clickable": false, 
                              "pressed": "not_pressed", 
                              "text": "Release Date:", 
                              "focusable": false, 
                              "long-clickable": false, 
                              "enabled": true, 
                              "bounds": [
                                378, 
                                256, 
                                723, 
                                332
                              ], 
                              "visibility": "visible", 
                              "content-desc": [
                                null
                              ], 
                              "rel-bounds": [
                                0, 
                                0, 
                                345, 
                                76
                              ], 
                              "focused": false, 
                              "selected": false, 
                              "scrollable-vertical": false, 
                              "adapter-view": false, 
                              "abs-pos": true, 
                              "pointer": "17cb7f8", 
                              "class": "android.widget.TextView", 
                              "visible-to-user": true
                            }, 
                            {
                              "text": "Oct 21, 2015", 
                              "resource-id": "com.zonewalker.acar:id/app_release_date", 
                              "adapter-view": false, 
                              "pointer": "3f814d1", 
                              "scrollable-horizontal": false, 
                              "ancestors": [
                                "android.view.View", 
                                "java.lang.Object"
                              ], 
                              "selected": false, 
                              "content-desc": [
                                null
                              ], 
                              "rel-bounds": [
                                363, 
                                0, 
                                684, 
                                76
                              ], 
                              "draw": false, 
                              "focusable": false, 
                              "long-clickable": false, 
                              "visibility": "visible", 
                              "focused": false, 
                              "clickable": false, 
                              "abs-pos": true, 
                              "class": "android.widget.TextView", 
                              "visible-to-user": true, 
                              "package": "com.zonewalker.acar", 
                              "enabled": true, 
                              "bounds": [
                                741, 
                                256, 
                                1062, 
                                332
                              ], 
                              "pressed": "not_pressed", 
                              "scrollable-vertical": false
                            }
                          ], 
                          "adapter-view": false, 
                          "abs-pos": true, 
                          "pointer": "1c4e35b", 
                          "class": "android.widget.LinearLayout", 
                          "visible-to-user": true
                        }, 
                        {
                          "scrollable-horizontal": false, 
                          "draw": true, 
                          "ancestors": [
                            "android.view.ViewGroup", 
                            "android.view.View", 
                            "java.lang.Object"
                          ], 
                          "clickable": false, 
                          "pressed": "not_pressed", 
                          "focusable": false, 
                          "long-clickable": false, 
                          "enabled": true, 
                          "bounds": [
                            542, 
                            332, 
                            897, 
                            408
                          ], 
                          "visibility": "visible", 
                          "content-desc": [
                            null
                          ], 
                          "rel-bounds": [
                            542, 
                            101, 
                            897, 
                            177
                          ], 
                          "focused": false, 
                          "selected": false, 
                          "scrollable-vertical": false, 
                          "children": [
                            {
                              "scrollable-horizontal": false, 
                              "draw": false, 
                              "ancestors": [
                                "android.view.View", 
                                "java.lang.Object"
                              ], 
                              "clickable": false, 
                              "pressed": "not_pressed", 
                              "text": "Version:", 
                              "focusable": false, 
                              "long-clickable": false, 
                              "enabled": true, 
                              "bounds": [
                                542, 
                                332, 
                                751, 
                                408
                              ], 
                              "visibility": "visible", 
                              "content-desc": [
                                null
                              ], 
                              "rel-bounds": [
                                0, 
                                0, 
                                209, 
                                76
                              ], 
                              "focused": false, 
                              "selected": false, 
                              "scrollable-vertical": false, 
                              "adapter-view": false, 
                              "abs-pos": true, 
                              "pointer": "f645a37", 
                              "class": "android.widget.TextView", 
                              "visible-to-user": true
                            }, 
                            {
                              "text": "4.8.6", 
                              "resource-id": "com.zonewalker.acar:id/app_version", 
                              "adapter-view": false, 
                              "pointer": "ec15ba4", 
                              "scrollable-horizontal": false, 
                              "ancestors": [
                                "android.view.View", 
                                "java.lang.Object"
                              ], 
                              "selected": false, 
                              "content-desc": [
                                null
                              ], 
                              "rel-bounds": [
                                227, 
                                0, 
                                355, 
                                76
                              ], 
                              "draw": false, 
                              "focusable": false, 
                              "long-clickable": false, 
                              "visibility": "visible", 
                              "focused": false, 
                              "clickable": false, 
                              "abs-pos": true, 
                              "class": "android.widget.TextView", 
                              "visible-to-user": true, 
                              "package": "com.zonewalker.acar", 
                              "enabled": true, 
                              "bounds": [
                                769, 
                                332, 
                                897, 
                                408
                              ], 
                              "pressed": "not_pressed", 
                              "scrollable-vertical": false
                            }
                          ], 
                          "adapter-view": false, 
                          "abs-pos": true, 
                          "pointer": "19ebb36", 
                          "class": "android.widget.LinearLayout", 
                          "visible-to-user": true
                        }, 
                        {
                          "scrollable-horizontal": false, 
                          "draw": true, 
                          "ancestors": [
                            "android.view.ViewGroup", 
                            "android.view.View", 
                            "java.lang.Object"
                          ], 
                          "clickable": false, 
                          "pressed": "not_pressed", 
                          "focusable": false, 
                          "long-clickable": false, 
                          "enabled": true, 
                          "bounds": [
                            484, 
                            408, 
                            956, 
                            484
                          ], 
                          "visibility": "visible", 
                          "content-desc": [
                            null
                          ], 
                          "rel-bounds": [
                            484, 
                            177, 
                            956, 
                            253
                          ], 
                          "focused": false, 
                          "selected": false, 
                          "scrollable-vertical": false, 
                          "children": [
                            {
                              "scrollable-horizontal": false, 
                              "draw": false, 
                              "ancestors": [
                                "android.view.View", 
                                "java.lang.Object"
                              ], 
                              "clickable": false, 
                              "pressed": "not_pressed", 
                              "text": "Author:", 
                              "focusable": false, 
                              "long-clickable": false, 
                              "enabled": true, 
                              "bounds": [
                                484, 
                                408, 
                                671, 
                                484
                              ], 
                              "visibility": "visible", 
                              "content-desc": [
                                null
                              ], 
                              "rel-bounds": [
                                0, 
                                0, 
                                187, 
                                76
                              ], 
                              "focused": false, 
                              "selected": false, 
                              "scrollable-vertical": false, 
                              "adapter-view": false, 
                              "abs-pos": true, 
                              "pointer": "81354c2", 
                              "class": "android.widget.TextView", 
                              "visible-to-user": true
                            }, 
                            {
                              "scrollable-horizontal": false, 
                              "draw": false, 
                              "ancestors": [
                                "android.view.View", 
                                "java.lang.Object"
                              ], 
                              "clickable": false, 
                              "pressed": "not_pressed", 
                              "text": "Fuelly, LLC", 
                              "focusable": false, 
                              "long-clickable": false, 
                              "enabled": true, 
                              "bounds": [
                                689, 
                                408, 
                                956, 
                                484
                              ], 
                              "visibility": "visible", 
                              "content-desc": [
                                null
                              ], 
                              "rel-bounds": [
                                205, 
                                0, 
                                472, 
                                76
                              ], 
                              "focused": false, 
                              "selected": false, 
                              "scrollable-vertical": false, 
                              "adapter-view": false, 
                              "abs-pos": true, 
                              "pointer": "41a62d3", 
                              "class": "android.widget.TextView", 
                              "visible-to-user": true
                            }
                          ], 
                          "adapter-view": false, 
                          "abs-pos": true, 
                          "pointer": "7182d0d", 
                          "class": "android.widget.LinearLayout", 
                          "visible-to-user": true
                        }, 
                        {
                          "scrollable-horizontal": false, 
                          "draw": false, 
                          "ancestors": [
                            "android.view.View", 
                            "java.lang.Object"
                          ], 
                          "clickable": false, 
                          "pressed": "not_pressed", 
                          "text": "aCar is an all-in-one handy application to effectively track the fuel mileage and costs, maintenance, business trips/mileages and general expenses of your vehicles.", 
                          "focusable": false, 
                          "long-clickable": false, 
                          "enabled": true, 
                          "bounds": [
                            25, 
                            554, 
                            1415, 
                            828
                          ], 
                          "visibility": "visible", 
                          "content-desc": [
                            null
                          ], 
                          "rel-bounds": [
                            25, 
                            323, 
                            1415, 
                            597
                          ], 
                          "focused": false, 
                          "selected": false, 
                          "scrollable-vertical": false, 
                          "adapter-view": false, 
                          "abs-pos": true, 
                          "pointer": "b8a8e10", 
                          "class": "android.widget.TextView", 
                          "visible-to-user": true
                        }, 
                        {
                          "scrollable-horizontal": false, 
                          "draw": false, 
                          "ancestors": [
                            "android.view.View", 
                            "java.lang.Object"
                          ], 
                          "clickable": false, 
                          "pressed": "not_pressed", 
                          "text": "Whether you want to track the fuel mileage, expenses or maintenance of your vehicles, or to simply know if your vehicles operate at their maximum performance, aCar is the right tool for you.", 
                          "focusable": false, 
                          "long-clickable": false, 
                          "enabled": true, 
                          "bounds": [
                            25, 
                            863, 
                            1415, 
                            1137
                          ], 
                          "visibility": "visible", 
                          "content-desc": [
                            null
                          ], 
                          "rel-bounds": [
                            25, 
                            632, 
                            1415, 
                            906
                          ], 
                          "focused": false, 
                          "selected": false, 
                          "scrollable-vertical": false, 
                          "adapter-view": false, 
                          "abs-pos": true, 
                          "pointer": "1a78d09", 
                          "class": "android.widget.TextView", 
                          "visible-to-user": true
                        }, 
                        {
                          "scrollable-horizontal": false, 
                          "draw": false, 
                          "ancestors": [
                            "android.view.View", 
                            "java.lang.Object"
                          ], 
                          "clickable": false, 
                          "pressed": "not_pressed", 
                          "text": "aCar will provide you tons of detailed statistics, information and graphical charts/reports to inform you how your vehicles are performing at any given moment.", 
                          "focusable": false, 
                          "long-clickable": false, 
                          "enabled": true, 
                          "bounds": [
                            25, 
                            1155, 
                            1415, 
                            1363
                          ], 
                          "visibility": "visible", 
                          "content-desc": [
                            null
                          ], 
                          "rel-bounds": [
                            25, 
                            924, 
                            1415, 
                            1132
                          ], 
                          "focused": false, 
                          "selected": false, 
                          "scrollable-vertical": false, 
                          "adapter-view": false, 
                          "abs-pos": true, 
                          "pointer": "f45fb0e", 
                          "class": "android.widget.TextView", 
                          "visible-to-user": true
                        }, 
                        {
                          "scrollable-horizontal": false, 
                          "draw": false, 
                          "ancestors": [
                            "android.view.View", 
                            "java.lang.Object"
                          ], 
                          "clickable": false, 
                          "pressed": "not_pressed", 
                          "text": "You will never miss a maintenance service (be it changing air filter, engine oil or inspection, etc) using the highly customizable reminders even if aCar is not running!", 
                          "focusable": false, 
                          "long-clickable": false, 
                          "enabled": true, 
                          "bounds": [
                            25, 
                            1381, 
                            1415, 
                            1655
                          ], 
                          "visibility": "visible", 
                          "content-desc": [
                            null
                          ], 
                          "rel-bounds": [
                            25, 
                            1150, 
                            1415, 
                            1424
                          ], 
                          "focused": false, 
                          "selected": false, 
                          "scrollable-vertical": false, 
                          "adapter-view": false, 
                          "abs-pos": true, 
                          "pointer": "e1e592f", 
                          "class": "android.widget.TextView", 
                          "visible-to-user": true
                        }, 
                        {
                          "scrollable-horizontal": false, 
                          "draw": false, 
                          "ancestors": [
                            "android.view.View", 
                            "java.lang.Object"
                          ], 
                          "clickable": false, 
                          "pressed": "not_pressed", 
                          "text": "You can also track your business (and non-business) trips and mileages in detail.", 
                          "focusable": false, 
                          "long-clickable": false, 
                          "enabled": true, 
                          "bounds": [
                            25, 
                            1673, 
                            1415, 
                            1815
                          ], 
                          "visibility": "visible", 
                          "content-desc": [
                            null
                          ], 
                          "rel-bounds": [
                            25, 
                            1442, 
                            1415, 
                            1584
                          ], 
                          "focused": false, 
                          "selected": false, 
                          "scrollable-vertical": false, 
                          "adapter-view": false, 
                          "abs-pos": true, 
                          "pointer": "b727b3c", 
                          "class": "android.widget.TextView", 
                          "visible-to-user": true
                        }, 
                        {
                          "scrollable-horizontal": false, 
                          "draw": true, 
                          "ancestors": [
                            "android.view.ViewGroup", 
                            "android.view.View", 
                            "java.lang.Object"
                          ], 
                          "clickable": false, 
                          "pressed": "not_pressed", 
                          "focusable": false, 
                          "long-clickable": false, 
                          "enabled": true, 
                          "bounds": [
                            245, 
                            1833, 
                            1195, 
                            2023
                          ], 
                          "visibility": "visible", 
                          "content-desc": [
                            null
                          ], 
                          "rel-bounds": [
                            245, 
                            1602, 
                            1195, 
                            1792
                          ], 
                          "focused": false, 
                          "selected": false, 
                          "scrollable-vertical": false, 
                          "children": [
                            {
                              "resource-id": "com.zonewalker.acar:id/img_facebook", 
                              "adapter-view": false, 
                              "pointer": "7eaba1a", 
                              "scrollable-horizontal": false, 
                              "ancestors": [
                                "android.view.View", 
                                "java.lang.Object"
                              ], 
                              "selected": false, 
                              "content-desc": [
                                null
                              ], 
                              "rel-bounds": [
                                25, 
                                25, 
                                165, 
                                165
                              ], 
                              "draw": false, 
                              "focusable": false, 
                              "long-clickable": false, 
                              "visibility": "visible", 
                              "focused": false, 
                              "clickable": true, 
                              "abs-pos": true, 
                              "class": "android.widget.ImageView", 
                              "visible-to-user": true, 
                              "package": "com.zonewalker.acar", 
                              "enabled": true, 
                              "bounds": [
                                270, 
                                1858, 
                                410, 
                                1998
                              ], 
                              "pressed": "not_pressed", 
                              "scrollable-vertical": false
                            }, 
                            {
                              "resource-id": "com.zonewalker.acar:id/img_twitter", 
                              "adapter-view": false, 
                              "pointer": "dc1594b", 
                              "scrollable-horizontal": false, 
                              "ancestors": [
                                "android.view.View", 
                                "java.lang.Object"
                              ], 
                              "selected": false, 
                              "content-desc": [
                                null
                              ], 
                              "rel-bounds": [
                                215, 
                                25, 
                                355, 
                                165
                              ], 
                              "draw": false, 
                              "focusable": false, 
                              "long-clickable": false, 
                              "visibility": "visible", 
                              "focused": false, 
                              "clickable": true, 
                              "abs-pos": true, 
                              "class": "android.widget.ImageView", 
                              "visible-to-user": true, 
                              "package": "com.zonewalker.acar", 
                              "enabled": true, 
                              "bounds": [
                                460, 
                                1858, 
                                600, 
                                1998
                              ], 
                              "pressed": "not_pressed", 
                              "scrollable-vertical": false
                            }, 
                            {
                              "resource-id": "com.zonewalker.acar:id/img_google_plus", 
                              "adapter-view": false, 
                              "pointer": "f8a0f28", 
                              "scrollable-horizontal": false, 
                              "ancestors": [
                                "android.view.View", 
                                "java.lang.Object"
                              ], 
                              "selected": false, 
                              "content-desc": [
                                null
                              ], 
                              "rel-bounds": [
                                405, 
                                25, 
                                545, 
                                165
                              ], 
                              "draw": false, 
                              "focusable": false, 
                              "long-clickable": false, 
                              "visibility": "visible", 
                              "focused": false, 
                              "clickable": true, 
                              "abs-pos": true, 
                              "class": "android.widget.ImageView", 
                              "visible-to-user": true, 
                              "package": "com.zonewalker.acar", 
                              "enabled": true, 
                              "bounds": [
                                650, 
                                1858, 
                                790, 
                                1998
                              ], 
                              "pressed": "not_pressed", 
                              "scrollable-vertical": false
                            }, 
                            {
                              "resource-id": "com.zonewalker.acar:id/img_website", 
                              "adapter-view": false, 
                              "pointer": "f56d441", 
                              "scrollable-horizontal": false, 
                              "ancestors": [
                                "android.view.View", 
                                "java.lang.Object"
                              ], 
                              "selected": false, 
                              "content-desc": [
                                null
                              ], 
                              "rel-bounds": [
                                595, 
                                25, 
                                735, 
                                165
                              ], 
                              "draw": false, 
                              "focusable": false, 
                              "long-clickable": false, 
                              "visibility": "visible", 
                              "focused": false, 
                              "clickable": true, 
                              "abs-pos": true, 
                              "class": "android.widget.ImageView", 
                              "visible-to-user": true, 
                              "package": "com.zonewalker.acar", 
                              "enabled": true, 
                              "bounds": [
                                840, 
                                1858, 
                                980, 
                                1998
                              ], 
                              "pressed": "not_pressed", 
                              "scrollable-vertical": false
                            }, 
                            {
                              "resource-id": "com.zonewalker.acar:id/img_contact_support", 
                              "adapter-view": false, 
                              "pointer": "7ea5de6", 
                              "scrollable-horizontal": false, 
                              "ancestors": [
                                "android.view.View", 
                                "java.lang.Object"
                              ], 
                              "selected": false, 
                              "content-desc": [
                                null
                              ], 
                              "rel-bounds": [
                                785, 
                                25, 
                                925, 
                                165
                              ], 
                              "draw": false, 
                              "focusable": false, 
                              "long-clickable": false, 
                              "visibility": "visible", 
                              "focused": false, 
                              "clickable": true, 
                              "abs-pos": true, 
                              "class": "android.widget.ImageView", 
                              "visible-to-user": true, 
                              "package": "com.zonewalker.acar", 
                              "enabled": true, 
                              "bounds": [
                                1030, 
                                1858, 
                                1170, 
                                1998
                              ], 
                              "pressed": "not_pressed", 
                              "scrollable-vertical": false
                            }
                          ], 
                          "adapter-view": false, 
                          "abs-pos": true, 
                          "pointer": "db2f0c5", 
                          "class": "android.widget.LinearLayout", 
                          "visible-to-user": true
                        }, 
                        {
                          "text": "http://www.fuelly.com/acar", 
                          "resource-id": "com.zonewalker.acar:id/app_website", 
                          "adapter-view": false, 
                          "pointer": "d4a3f27", 
                          "scrollable-horizontal": false, 
                          "ancestors": [
                            "android.view.View", 
                            "java.lang.Object"
                          ], 
                          "selected": false, 
                          "content-desc": [
                            null
                          ], 
                          "rel-bounds": [
                            381, 
                            1792, 
                            1058, 
                            1868
                          ], 
                          "draw": false, 
                          "focusable": true, 
                          "long-clickable": true, 
                          "visibility": "visible", 
                          "focused": false, 
                          "clickable": true, 
                          "abs-pos": true, 
                          "class": "android.widget.TextView", 
                          "visible-to-user": true, 
                          "package": "com.zonewalker.acar", 
                          "enabled": true, 
                          "bounds": [
                            381, 
                            2023, 
                            1058, 
                            2099
                          ], 
                          "pressed": "not_pressed", 
                          "scrollable-vertical": false
                        }
                      ], 
                      "adapter-view": false, 
                      "abs-pos": true, 
                      "pointer": "29ce26a", 
                      "class": "android.widget.LinearLayout", 
                      "visible-to-user": true
                    }
                  ], 
                  "adapter-view": false, 
                  "abs-pos": true, 
                  "pointer": "2ce4855", 
                  "class": "android.widget.ScrollView", 
                  "visible-to-user": true
                }
              ], 
              "scrollable-horizontal": false, 
              "ancestors": [
                "android.view.ViewGroup", 
                "android.view.View", 
                "java.lang.Object"
              ], 
              "selected": false, 
              "content-desc": [
                null
              ], 
              "rel-bounds": [
                0, 
                231, 
                1440, 
                2392
              ], 
              "draw": true, 
              "focusable": false, 
              "long-clickable": false, 
              "visibility": "visible", 
              "focused": false, 
              "clickable": false, 
              "abs-pos": true, 
              "class": "android.widget.FrameLayout", 
              "visible-to-user": true, 
              "package": "android", 
              "enabled": true, 
              "bounds": [
                0, 
                231, 
                1440, 
                2392
              ], 
              "pressed": "not_pressed", 
              "scrollable-vertical": false
            }
          ], 
          "adapter-view": false, 
          "abs-pos": true, 
          "pointer": "9cde457", 
          "class": "android.widget.LinearLayout", 
          "visible-to-user": true
        }
      ], 
      "adapter-view": false, 
      "abs-pos": true, 
      "pointer": "2d99d6", 
      "class": "com.android.internal.policy.PhoneWindow$DecorView", 
      "visible-to-user": true
    }, 
    "added_fragments": [], 
    "active_fragments": []
  }, 
  "is_keyboard_deployed": false, 
  "request_id": "101"
}