{
  "activity_name": "com.kauf.sticker.funfacechangerproeffects/com.kauf.inapp.sticker.TextActivity", 
  "activity": {
    "root": {
      "scrollable-horizontal": false, 
      "draw": true, 
      "ancestors": [
        "android.widget.FrameLayout", 
        "android.view.ViewGroup", 
        "android.view.View", 
        "java.lang.Object"
      ], 
      "clickable": false, 
      "pressed": "not_pressed", 
      "focusable": false, 
      "long-clickable": false, 
      "enabled": true, 
      "bounds": [
        0, 
        0, 
        1440, 
        2392
      ], 
      "visibility": "visible", 
      "content-desc": [
        null
      ], 
      "rel-bounds": [
        0, 
        0, 
        1440, 
        2392
      ], 
      "focused": false, 
      "selected": false, 
      "scrollable-vertical": false, 
      "children": [
        {
          "scrollable-horizontal": false, 
          "draw": true, 
          "ancestors": [
            "android.view.ViewGroup", 
            "android.view.View", 
            "java.lang.Object"
          ], 
          "clickable": false, 
          "pressed": "not_pressed", 
          "focusable": false, 
          "long-clickable": false, 
          "enabled": true, 
          "bounds": [
            0, 
            0, 
            1440, 
            2392
          ], 
          "visibility": "visible", 
          "content-desc": [
            null
          ], 
          "rel-bounds": [
            0, 
            0, 
            1440, 
            2392
          ], 
          "focused": false, 
          "selected": false, 
          "scrollable-vertical": false, 
          "children": [
            {
              "resource-id": "android:id/action_mode_bar_stub", 
              "adapter-view": false, 
              "pointer": "4bf0440", 
              "scrollable-horizontal": false, 
              "ancestors": [
                "android.view.View", 
                "java.lang.Object"
              ], 
              "selected": false, 
              "content-desc": [
                null
              ], 
              "rel-bounds": [
                0, 
                0, 
                0, 
                0
              ], 
              "draw": true, 
              "focusable": false, 
              "long-clickable": false, 
              "visibility": "gone", 
              "focused": false, 
              "clickable": false, 
              "abs-pos": true, 
              "class": "android.view.ViewStub", 
              "visible-to-user": false, 
              "package": "android", 
              "enabled": true, 
              "bounds": [
                0, 
                0, 
                0, 
                0
              ], 
              "pressed": "not_pressed", 
              "scrollable-vertical": false
            }, 
            {
              "resource-id": "android:id/content", 
              "adapter-view": false, 
              "pointer": "2207f79", 
              "children": [
                {
                  "scrollable-horizontal": false, 
                  "draw": false, 
                  "ancestors": [
                    "android.widget.FrameLayout", 
                    "android.view.ViewGroup", 
                    "android.view.View", 
                    "java.lang.Object"
                  ], 
                  "clickable": false, 
                  "pressed": "not_pressed", 
                  "focusable": true, 
                  "long-clickable": false, 
                  "enabled": true, 
                  "bounds": [
                    0, 
                    0, 
                    1440, 
                    2392
                  ], 
                  "visibility": "visible", 
                  "content-desc": [
                    null
                  ], 
                  "rel-bounds": [
                    0, 
                    0, 
                    1440, 
                    2392
                  ], 
                  "focused": false, 
                  "selected": false, 
                  "scrollable-vertical": true, 
                  "children": [
                    {
                      "scrollable-horizontal": false, 
                      "draw": true, 
                      "ancestors": [
                        "android.view.ViewGroup", 
                        "android.view.View", 
                        "java.lang.Object"
                      ], 
                      "clickable": false, 
                      "pressed": "not_pressed", 
                      "focusable": false, 
                      "long-clickable": false, 
                      "enabled": true, 
                      "bounds": [
                        0, 
                        0, 
                        1440, 
                        2392
                      ], 
                      "visibility": "visible", 
                      "content-desc": [
                        null
                      ], 
                      "rel-bounds": [
                        0, 
                        0, 
                        1440, 
                        2566
                      ], 
                      "focused": false, 
                      "selected": false, 
                      "scrollable-vertical": false, 
                      "children": [
                        {
                          "scrollable-horizontal": false, 
                          "draw": false, 
                          "ancestors": [
                            "android.view.View", 
                            "java.lang.Object"
                          ], 
                          "clickable": false, 
                          "pressed": "not_pressed", 
                          "text": "Text", 
                          "focusable": false, 
                          "long-clickable": false, 
                          "enabled": true, 
                          "bounds": [
                            18, 
                            18, 
                            138, 
                            103
                          ], 
                          "visibility": "visible", 
                          "content-desc": [
                            null
                          ], 
                          "rel-bounds": [
                            18, 
                            18, 
                            138, 
                            103
                          ], 
                          "focused": false, 
                          "selected": false, 
                          "scrollable-vertical": false, 
                          "adapter-view": false, 
                          "abs-pos": true, 
                          "pointer": "3b0246c", 
                          "class": "android.widget.TextView", 
                          "visible-to-user": true
                        }, 
                        {
                          "text": "j", 
                          "resource-id": "com.kauf.sticker.funfacechangerproeffects:id/EditTextStickerText", 
                          "adapter-view": false, 
                          "pointer": "4a09a35", 
                          "scrollable-horizontal": false, 
                          "ancestors": [
                            "android.widget.TextView", 
                            "android.view.View", 
                            "java.lang.Object"
                          ], 
                          "selected": false, 
                          "content-desc": [
                            null
                          ], 
                          "rel-bounds": [
                            18, 
                            103, 
                            1422, 
                            241
                          ], 
                          "draw": false, 
                          "focusable": true, 
                          "long-clickable": true, 
                          "visibility": "visible", 
                          "text-hint": "your text", 
                          "focused": true, 
                          "clickable": true, 
                          "abs-pos": true, 
                          "class": "android.widget.EditText", 
                          "visible-to-user": true, 
                          "package": "com.kauf.sticker.funfacechangerproeffects", 
                          "enabled": true, 
                          "bounds": [
                            18, 
                            103, 
                            1422, 
                            241
                          ], 
                          "pressed": "not_pressed", 
                          "scrollable-vertical": false
                        }, 
                        {
                          "scrollable-horizontal": false, 
                          "draw": false, 
                          "ancestors": [
                            "android.view.View", 
                            "java.lang.Object"
                          ], 
                          "clickable": false, 
                          "pressed": "not_pressed", 
                          "text": "Text size", 
                          "focusable": false, 
                          "long-clickable": false, 
                          "enabled": true, 
                          "bounds": [
                            18, 
                            311, 
                            265, 
                            396
                          ], 
                          "visibility": "visible", 
                          "content-desc": [
                            null
                          ], 
                          "rel-bounds": [
                            18, 
                            311, 
                            265, 
                            396
                          ], 
                          "focused": false, 
                          "selected": false, 
                          "scrollable-vertical": false, 
                          "adapter-view": false, 
                          "abs-pos": true, 
                          "pointer": "15bfeca", 
                          "class": "android.widget.TextView", 
                          "visible-to-user": true
                        }, 
                        {
                          "scrollable-horizontal": false, 
                          "draw": true, 
                          "ancestors": [
                            "android.view.ViewGroup", 
                            "android.view.View", 
                            "java.lang.Object"
                          ], 
                          "clickable": false, 
                          "pressed": "not_pressed", 
                          "focusable": false, 
                          "long-clickable": false, 
                          "enabled": true, 
                          "bounds": [
                            18, 
                            396, 
                            1422, 
                            508
                          ], 
                          "visibility": "visible", 
                          "content-desc": [
                            null
                          ], 
                          "rel-bounds": [
                            18, 
                            396, 
                            1422, 
                            508
                          ], 
                          "focused": false, 
                          "selected": false, 
                          "scrollable-vertical": false, 
                          "children": [
                            {
                              "text": "50px", 
                              "resource-id": "com.kauf.sticker.funfacechangerproeffects:id/TextViewStickerTextSize", 
                              "adapter-view": false, 
                              "pointer": "9b11b58", 
                              "scrollable-horizontal": false, 
                              "ancestors": [
                                "android.view.View", 
                                "java.lang.Object"
                              ], 
                              "selected": false, 
                              "content-desc": [
                                null
                              ], 
                              "rel-bounds": [
                                0, 
                                0, 
                                402, 
                                103
                              ], 
                              "draw": false, 
                              "focusable": false, 
                              "long-clickable": false, 
                              "visibility": "visible", 
                              "focused": false, 
                              "clickable": false, 
                              "abs-pos": true, 
                              "class": "android.widget.TextView", 
                              "visible-to-user": true, 
                              "package": "com.kauf.sticker.funfacechangerproeffects", 
                              "enabled": true, 
                              "bounds": [
                                18, 
                                396, 
                                420, 
                                499
                              ], 
                              "pressed": "not_pressed", 
                              "scrollable-vertical": false
                            }, 
                            {
                              "resource-id": "com.kauf.sticker.funfacechangerproeffects:id/SeekBarStickerTextSize", 
                              "adapter-view": false, 
                              "pointer": "4cda4b1", 
                              "scrollable-horizontal": false, 
                              "ancestors": [
                                "android.widget.AbsSeekBar", 
                                "android.widget.ProgressBar", 
                                "android.view.View", 
                                "java.lang.Object"
                              ], 
                              "selected": false, 
                              "content-desc": [
                                null
                              ], 
                              "rel-bounds": [
                                402, 
                                0, 
                                1404, 
                                112
                              ], 
                              "draw": false, 
                              "focusable": true, 
                              "long-clickable": false, 
                              "visibility": "visible", 
                              "focused": false, 
                              "clickable": false, 
                              "abs-pos": true, 
                              "class": "android.widget.SeekBar", 
                              "visible-to-user": true, 
                              "package": "com.kauf.sticker.funfacechangerproeffects", 
                              "enabled": true, 
                              "bounds": [
                                420, 
                                396, 
                                1422, 
                                508
                              ], 
                              "pressed": "not_pressed", 
                              "scrollable-vertical": false
                            }
                          ], 
                          "adapter-view": false, 
                          "abs-pos": true, 
                          "pointer": "609383b", 
                          "class": "android.widget.LinearLayout", 
                          "visible-to-user": true
                        }, 
                        {
                          "scrollable-horizontal": false, 
                          "draw": false, 
                          "ancestors": [
                            "android.view.View", 
                            "java.lang.Object"
                          ], 
                          "clickable": false, 
                          "pressed": "not_pressed", 
                          "text": "Text color", 
                          "focusable": false, 
                          "long-clickable": false, 
                          "enabled": true, 
                          "bounds": [
                            18, 
                            578, 
                            295, 
                            663
                          ], 
                          "visibility": "visible", 
                          "content-desc": [
                            null
                          ], 
                          "rel-bounds": [
                            18, 
                            578, 
                            295, 
                            663
                          ], 
                          "focused": false, 
                          "selected": false, 
                          "scrollable-vertical": false, 
                          "adapter-view": false, 
                          "abs-pos": true, 
                          "pointer": "5a33d96", 
                          "class": "android.widget.TextView", 
                          "visible-to-user": true
                        }, 
                        {
                          "scrollable-horizontal": false, 
                          "draw": true, 
                          "ancestors": [
                            "android.view.ViewGroup", 
                            "android.view.View", 
                            "java.lang.Object"
                          ], 
                          "clickable": false, 
                          "pressed": "not_pressed", 
                          "focusable": false, 
                          "long-clickable": false, 
                          "enabled": true, 
                          "bounds": [
                            18, 
                            663, 
                            1422, 
                            1506
                          ], 
                          "visibility": "visible", 
                          "content-desc": [
                            null
                          ], 
                          "rel-bounds": [
                            18, 
                            663, 
                            1422, 
                            1506
                          ], 
                          "focused": false, 
                          "selected": false, 
                          "scrollable-vertical": false, 
                          "children": [
                            {
                              "scrollable-horizontal": false, 
                              "draw": true, 
                              "ancestors": [
                                "android.view.ViewGroup", 
                                "android.view.View", 
                                "java.lang.Object"
                              ], 
                              "clickable": false, 
                              "pressed": "not_pressed", 
                              "focusable": false, 
                              "long-clickable": false, 
                              "enabled": true, 
                              "bounds": [
                                18, 
                                663, 
                                1422, 
                                944
                              ], 
                              "visibility": "visible", 
                              "content-desc": [
                                null
                              ], 
                              "rel-bounds": [
                                0, 
                                0, 
                                1404, 
                                281
                              ], 
                              "focused": false, 
                              "selected": false, 
                              "scrollable-vertical": false, 
                              "children": [
                                {
                                  "resource-id": "com.kauf.sticker.funfacechangerproeffects:id/ImageViewStickerColor1", 
                                  "adapter-view": false, 
                                  "pointer": "6e6daed", 
                                  "scrollable-horizontal": false, 
                                  "ancestors": [
                                    "android.view.View", 
                                    "java.lang.Object"
                                  ], 
                                  "selected": false, 
                                  "content-desc": [
                                    null
                                  ], 
                                  "rel-bounds": [
                                    0, 
                                    0, 
                                    281, 
                                    281
                                  ], 
                                  "draw": false, 
                                  "focusable": false, 
                                  "long-clickable": false, 
                                  "visibility": "visible", 
                                  "focused": false, 
                                  "clickable": true, 
                                  "abs-pos": true, 
                                  "class": "android.widget.ImageView", 
                                  "visible-to-user": true, 
                                  "package": "com.kauf.sticker.funfacechangerproeffects", 
                                  "enabled": true, 
                                  "bounds": [
                                    18, 
                                    663, 
                                    299, 
                                    944
                                  ], 
                                  "pressed": "not_pressed", 
                                  "scrollable-vertical": false
                                }, 
                                {
                                  "resource-id": "com.kauf.sticker.funfacechangerproeffects:id/ImageViewStickerColor2", 
                                  "adapter-view": false, 
                                  "pointer": "74d9d22", 
                                  "scrollable-horizontal": false, 
                                  "ancestors": [
                                    "android.view.View", 
                                    "java.lang.Object"
                                  ], 
                                  "selected": false, 
                                  "content-desc": [
                                    null
                                  ], 
                                  "rel-bounds": [
                                    281, 
                                    0, 
                                    562, 
                                    281
                                  ], 
                                  "draw": false, 
                                  "focusable": false, 
                                  "long-clickable": false, 
                                  "visibility": "visible", 
                                  "focused": false, 
                                  "clickable": true, 
                                  "abs-pos": true, 
                                  "class": "android.widget.ImageView", 
                                  "visible-to-user": true, 
                                  "package": "com.kauf.sticker.funfacechangerproeffects", 
                                  "enabled": true, 
                                  "bounds": [
                                    299, 
                                    663, 
                                    580, 
                                    944
                                  ], 
                                  "pressed": "not_pressed", 
                                  "scrollable-vertical": false
                                }, 
                                {
                                  "resource-id": "com.kauf.sticker.funfacechangerproeffects:id/ImageViewStickerColor3", 
                                  "adapter-view": false, 
                                  "pointer": "c3873b3", 
                                  "scrollable-horizontal": false, 
                                  "ancestors": [
                                    "android.view.View", 
                                    "java.lang.Object"
                                  ], 
                                  "selected": false, 
                                  "content-desc": [
                                    null
                                  ], 
                                  "rel-bounds": [
                                    562, 
                                    0, 
                                    843, 
                                    281
                                  ], 
                                  "draw": false, 
                                  "focusable": false, 
                                  "long-clickable": false, 
                                  "visibility": "visible", 
                                  "focused": false, 
                                  "clickable": true, 
                                  "abs-pos": true, 
                                  "class": "android.widget.ImageView", 
                                  "visible-to-user": true, 
                                  "package": "com.kauf.sticker.funfacechangerproeffects", 
                                  "enabled": true, 
                                  "bounds": [
                                    580, 
                                    663, 
                                    861, 
                                    944
                                  ], 
                                  "pressed": "not_pressed", 
                                  "scrollable-vertical": false
                                }, 
                                {
                                  "resource-id": "com.kauf.sticker.funfacechangerproeffects:id/ImageViewStickerColor4", 
                                  "adapter-view": false, 
                                  "pointer": "6bbfd70", 
                                  "scrollable-horizontal": false, 
                                  "ancestors": [
                                    "android.view.View", 
                                    "java.lang.Object"
                                  ], 
                                  "selected": false, 
                                  "content-desc": [
                                    null
                                  ], 
                                  "rel-bounds": [
                                    843, 
                                    0, 
                                    1124, 
                                    281
                                  ], 
                                  "draw": false, 
                                  "focusable": false, 
                                  "long-clickable": false, 
                                  "visibility": "visible", 
                                  "focused": false, 
                                  "clickable": true, 
                                  "abs-pos": true, 
                                  "class": "android.widget.ImageView", 
                                  "visible-to-user": true, 
                                  "package": "com.kauf.sticker.funfacechangerproeffects", 
                                  "enabled": true, 
                                  "bounds": [
                                    861, 
                                    663, 
                                    1142, 
                                    944
                                  ], 
                                  "pressed": "not_pressed", 
                                  "scrollable-vertical": false
                                }, 
                                {
                                  "resource-id": "com.kauf.sticker.funfacechangerproeffects:id/ImageViewStickerColor5", 
                                  "adapter-view": false, 
                                  "pointer": "9e338e9", 
                                  "scrollable-horizontal": false, 
                                  "ancestors": [
                                    "android.view.View", 
                                    "java.lang.Object"
                                  ], 
                                  "selected": false, 
                                  "content-desc": [
                                    null
                                  ], 
                                  "rel-bounds": [
                                    1124, 
                                    0, 
                                    1404, 
                                    280
                                  ], 
                                  "draw": false, 
                                  "focusable": false, 
                                  "long-clickable": false, 
                                  "visibility": "visible", 
                                  "focused": false, 
                                  "clickable": true, 
                                  "abs-pos": true, 
                                  "class": "android.widget.ImageView", 
                                  "visible-to-user": true, 
                                  "package": "com.kauf.sticker.funfacechangerproeffects", 
                                  "enabled": true, 
                                  "bounds": [
                                    1142, 
                                    663, 
                                    1422, 
                                    943
                                  ], 
                                  "pressed": "not_pressed", 
                                  "scrollable-vertical": false
                                }
                              ], 
                              "adapter-view": false, 
                              "abs-pos": true, 
                              "pointer": "bc89504", 
                              "class": "android.widget.LinearLayout", 
                              "visible-to-user": true
                            }, 
                            {
                              "scrollable-horizontal": false, 
                              "draw": true, 
                              "ancestors": [
                                "android.view.ViewGroup", 
                                "android.view.View", 
                                "java.lang.Object"
                              ], 
                              "clickable": false, 
                              "pressed": "not_pressed", 
                              "focusable": false, 
                              "long-clickable": false, 
                              "enabled": true, 
                              "bounds": [
                                18, 
                                944, 
                                1422, 
                                1225
                              ], 
                              "visibility": "visible", 
                              "content-desc": [
                                null
                              ], 
                              "rel-bounds": [
                                0, 
                                281, 
                                1404, 
                                562
                              ], 
                              "focused": false, 
                              "selected": false, 
                              "scrollable-vertical": false, 
                              "children": [
                                {
                                  "resource-id": "com.kauf.sticker.funfacechangerproeffects:id/ImageViewStickerColor6", 
                                  "adapter-view": false, 
                                  "pointer": "7bc980f", 
                                  "scrollable-horizontal": false, 
                                  "ancestors": [
                                    "android.view.View", 
                                    "java.lang.Object"
                                  ], 
                                  "selected": false, 
                                  "content-desc": [
                                    null
                                  ], 
                                  "rel-bounds": [
                                    0, 
                                    0, 
                                    281, 
                                    281
                                  ], 
                                  "draw": false, 
                                  "focusable": false, 
                                  "long-clickable": false, 
                                  "visibility": "visible", 
                                  "focused": false, 
                                  "clickable": true, 
                                  "abs-pos": true, 
                                  "class": "android.widget.ImageView", 
                                  "visible-to-user": true, 
                                  "package": "com.kauf.sticker.funfacechangerproeffects", 
                                  "enabled": true, 
                                  "bounds": [
                                    18, 
                                    944, 
                                    299, 
                                    1225
                                  ], 
                                  "pressed": "not_pressed", 
                                  "scrollable-vertical": false
                                }, 
                                {
                                  "resource-id": "com.kauf.sticker.funfacechangerproeffects:id/ImageViewStickerColor7", 
                                  "adapter-view": false, 
                                  "pointer": "c3b809c", 
                                  "scrollable-horizontal": false, 
                                  "ancestors": [
                                    "android.view.View", 
                                    "java.lang.Object"
                                  ], 
                                  "selected": false, 
                                  "content-desc": [
                                    null
                                  ], 
                                  "rel-bounds": [
                                    281, 
                                    0, 
                                    562, 
                                    281
                                  ], 
                                  "draw": false, 
                                  "focusable": false, 
                                  "long-clickable": false, 
                                  "visibility": "visible", 
                                  "focused": false, 
                                  "clickable": true, 
                                  "abs-pos": true, 
                                  "class": "android.widget.ImageView", 
                                  "visible-to-user": true, 
                                  "package": "com.kauf.sticker.funfacechangerproeffects", 
                                  "enabled": true, 
                                  "bounds": [
                                    299, 
                                    944, 
                                    580, 
                                    1225
                                  ], 
                                  "pressed": "not_pressed", 
                                  "scrollable-vertical": false
                                }, 
                                {
                                  "resource-id": "com.kauf.sticker.funfacechangerproeffects:id/ImageViewStickerColor8", 
                                  "adapter-view": false, 
                                  "pointer": "b2d7aa5", 
                                  "scrollable-horizontal": false, 
                                  "ancestors": [
                                    "android.view.View", 
                                    "java.lang.Object"
                                  ], 
                                  "selected": false, 
                                  "content-desc": [
                                    null
                                  ], 
                                  "rel-bounds": [
                                    562, 
                                    0, 
                                    843, 
                                    281
                                  ], 
                                  "draw": false, 
                                  "focusable": false, 
                                  "long-clickable": false, 
                                  "visibility": "visible", 
                                  "focused": false, 
                                  "clickable": true, 
                                  "abs-pos": true, 
                                  "class": "android.widget.ImageView", 
                                  "visible-to-user": true, 
                                  "package": "com.kauf.sticker.funfacechangerproeffects", 
                                  "enabled": true, 
                                  "bounds": [
                                    580, 
                                    944, 
                                    861, 
                                    1225
                                  ], 
                                  "pressed": "not_pressed", 
                                  "scrollable-vertical": false
                                }, 
                                {
                                  "resource-id": "com.kauf.sticker.funfacechangerproeffects:id/ImageViewStickerColor9", 
                                  "adapter-view": false, 
                                  "pointer": "e59ae7a", 
                                  "scrollable-horizontal": false, 
                                  "ancestors": [
                                    "android.view.View", 
                                    "java.lang.Object"
                                  ], 
                                  "selected": false, 
                                  "content-desc": [
                                    null
                                  ], 
                                  "rel-bounds": [
                                    843, 
                                    0, 
                                    1124, 
                                    281
                                  ], 
                                  "draw": false, 
                                  "focusable": false, 
                                  "long-clickable": false, 
                                  "visibility": "visible", 
                                  "focused": false, 
                                  "clickable": true, 
                                  "abs-pos": true, 
                                  "class": "android.widget.ImageView", 
                                  "visible-to-user": true, 
                                  "package": "com.kauf.sticker.funfacechangerproeffects", 
                                  "enabled": true, 
                                  "bounds": [
                                    861, 
                                    944, 
                                    1142, 
                                    1225
                                  ], 
                                  "pressed": "not_pressed", 
                                  "scrollable-vertical": false
                                }, 
                                {
                                  "resource-id": "com.kauf.sticker.funfacechangerproeffects:id/ImageViewStickerColor10", 
                                  "adapter-view": false, 
                                  "pointer": "bb4a62b", 
                                  "scrollable-horizontal": false, 
                                  "ancestors": [
                                    "android.view.View", 
                                    "java.lang.Object"
                                  ], 
                                  "selected": false, 
                                  "content-desc": [
                                    null
                                  ], 
                                  "rel-bounds": [
                                    1124, 
                                    0, 
                                    1404, 
                                    280
                                  ], 
                                  "draw": false, 
                                  "focusable": false, 
                                  "long-clickable": false, 
                                  "visibility": "visible", 
                                  "focused": false, 
                                  "clickable": true, 
                                  "abs-pos": true, 
                                  "class": "android.widget.ImageView", 
                                  "visible-to-user": true, 
                                  "package": "com.kauf.sticker.funfacechangerproeffects", 
                                  "enabled": true, 
                                  "bounds": [
                                    1142, 
                                    944, 
                                    1422, 
                                    1224
                                  ], 
                                  "pressed": "not_pressed", 
                                  "scrollable-vertical": false
                                }
                              ], 
                              "adapter-view": false, 
                              "abs-pos": true, 
                              "pointer": "e4c696e", 
                              "class": "android.widget.LinearLayout", 
                              "visible-to-user": true
                            }, 
                            {
                              "scrollable-horizontal": false, 
                              "draw": true, 
                              "ancestors": [
                                "android.view.ViewGroup", 
                                "android.view.View", 
                                "java.lang.Object"
                              ], 
                              "clickable": false, 
                              "pressed": "not_pressed", 
                              "focusable": false, 
                              "long-clickable": false, 
                              "enabled": true, 
                              "bounds": [
                                18, 
                                1225, 
                                1422, 
                                1506
                              ], 
                              "visibility": "visible", 
                              "content-desc": [
                                null
                              ], 
                              "rel-bounds": [
                                0, 
                                562, 
                                1404, 
                                843
                              ], 
                              "focused": false, 
                              "selected": false, 
                              "scrollable-vertical": false, 
                              "children": [
                                {
                                  "resource-id": "com.kauf.sticker.funfacechangerproeffects:id/ImageViewStickerColor11", 
                                  "adapter-view": false, 
                                  "pointer": "a201c21", 
                                  "scrollable-horizontal": false, 
                                  "ancestors": [
                                    "android.view.View", 
                                    "java.lang.Object"
                                  ], 
                                  "selected": false, 
                                  "content-desc": [
                                    null
                                  ], 
                                  "rel-bounds": [
                                    0, 
                                    0, 
                                    281, 
                                    281
                                  ], 
                                  "draw": false, 
                                  "focusable": false, 
                                  "long-clickable": false, 
                                  "visibility": "visible", 
                                  "focused": false, 
                                  "clickable": true, 
                                  "abs-pos": true, 
                                  "class": "android.widget.ImageView", 
                                  "visible-to-user": true, 
                                  "package": "com.kauf.sticker.funfacechangerproeffects", 
                                  "enabled": true, 
                                  "bounds": [
                                    18, 
                                    1225, 
                                    299, 
                                    1506
                                  ], 
                                  "pressed": "not_pressed", 
                                  "scrollable-vertical": false
                                }, 
                                {
                                  "resource-id": "com.kauf.sticker.funfacechangerproeffects:id/ImageViewStickerColor12", 
                                  "adapter-view": false, 
                                  "pointer": "ac43846", 
                                  "scrollable-horizontal": false, 
                                  "ancestors": [
                                    "android.view.View", 
                                    "java.lang.Object"
                                  ], 
                                  "selected": false, 
                                  "content-desc": [
                                    null
                                  ], 
                                  "rel-bounds": [
                                    281, 
                                    0, 
                                    562, 
                                    281
                                  ], 
                                  "draw": false, 
                                  "focusable": false, 
                                  "long-clickable": false, 
                                  "visibility": "visible", 
                                  "focused": false, 
                                  "clickable": true, 
                                  "abs-pos": true, 
                                  "class": "android.widget.ImageView", 
                                  "visible-to-user": true, 
                                  "package": "com.kauf.sticker.funfacechangerproeffects", 
                                  "enabled": true, 
                                  "bounds": [
                                    299, 
                                    1225, 
                                    580, 
                                    1506
                                  ], 
                                  "pressed": "not_pressed", 
                                  "scrollable-vertical": false
                                }, 
                                {
                                  "resource-id": "com.kauf.sticker.funfacechangerproeffects:id/ImageViewStickerColor13", 
                                  "adapter-view": false, 
                                  "pointer": "ad57a07", 
                                  "scrollable-horizontal": false, 
                                  "ancestors": [
                                    "android.view.View", 
                                    "java.lang.Object"
                                  ], 
                                  "selected": false, 
                                  "content-desc": [
                                    null
                                  ], 
                                  "rel-bounds": [
                                    562, 
                                    0, 
                                    843, 
                                    281
                                  ], 
                                  "draw": false, 
                                  "focusable": false, 
                                  "long-clickable": false, 
                                  "visibility": "visible", 
                                  "focused": false, 
                                  "clickable": true, 
                                  "abs-pos": true, 
                                  "class": "android.widget.ImageView", 
                                  "visible-to-user": true, 
                                  "package": "com.kauf.sticker.funfacechangerproeffects", 
                                  "enabled": true, 
                                  "bounds": [
                                    580, 
                                    1225, 
                                    861, 
                                    1506
                                  ], 
                                  "pressed": "not_pressed", 
                                  "scrollable-vertical": false
                                }, 
                                {
                                  "resource-id": "com.kauf.sticker.funfacechangerproeffects:id/ImageViewStickerColor14", 
                                  "adapter-view": false, 
                                  "pointer": "7d4734", 
                                  "scrollable-horizontal": false, 
                                  "ancestors": [
                                    "android.view.View", 
                                    "java.lang.Object"
                                  ], 
                                  "selected": false, 
                                  "content-desc": [
                                    null
                                  ], 
                                  "rel-bounds": [
                                    843, 
                                    0, 
                                    1124, 
                                    281
                                  ], 
                                  "draw": false, 
                                  "focusable": false, 
                                  "long-clickable": false, 
                                  "visibility": "visible", 
                                  "focused": false, 
                                  "clickable": true, 
                                  "abs-pos": true, 
                                  "class": "android.widget.ImageView", 
                                  "visible-to-user": true, 
                                  "package": "com.kauf.sticker.funfacechangerproeffects", 
                                  "enabled": true, 
                                  "bounds": [
                                    861, 
                                    1225, 
                                    1142, 
                                    1506
                                  ], 
                                  "pressed": "not_pressed", 
                                  "scrollable-vertical": false
                                }, 
                                {
                                  "resource-id": "com.kauf.sticker.funfacechangerproeffects:id/ImageViewStickerColor15", 
                                  "adapter-view": false, 
                                  "pointer": "741595d", 
                                  "scrollable-horizontal": false, 
                                  "ancestors": [
                                    "android.view.View", 
                                    "java.lang.Object"
                                  ], 
                                  "selected": false, 
                                  "content-desc": [
                                    null
                                  ], 
                                  "rel-bounds": [
                                    1124, 
                                    0, 
                                    1404, 
                                    280
                                  ], 
                                  "draw": false, 
                                  "focusable": false, 
                                  "long-clickable": false, 
                                  "visibility": "visible", 
                                  "focused": false, 
                                  "clickable": true, 
                                  "abs-pos": true, 
                                  "class": "android.widget.ImageView", 
                                  "visible-to-user": true, 
                                  "package": "com.kauf.sticker.funfacechangerproeffects", 
                                  "enabled": true, 
                                  "bounds": [
                                    1142, 
                                    1225, 
                                    1422, 
                                    1505
                                  ], 
                                  "pressed": "not_pressed", 
                                  "scrollable-vertical": false
                                }
                              ], 
                              "adapter-view": false, 
                              "abs-pos": true, 
                              "pointer": "6ce0a88", 
                              "class": "android.widget.LinearLayout", 
                              "visible-to-user": true
                            }
                          ], 
                          "adapter-view": false, 
                          "abs-pos": true, 
                          "pointer": "b491d17", 
                          "class": "android.widget.LinearLayout", 
                          "visible-to-user": true
                        }, 
                        {
                          "scrollable-horizontal": false, 
                          "draw": false, 
                          "ancestors": [
                            "android.view.View", 
                            "java.lang.Object"
                          ], 
                          "clickable": false, 
                          "pressed": "not_pressed", 
                          "text": "Fonttype", 
                          "focusable": false, 
                          "long-clickable": false, 
                          "enabled": true, 
                          "bounds": [
                            18, 
                            1576, 
                            263, 
                            1661
                          ], 
                          "visibility": "visible", 
                          "content-desc": [
                            null
                          ], 
                          "rel-bounds": [
                            18, 
                            1576, 
                            263, 
                            1661
                          ], 
                          "focused": false, 
                          "selected": false, 
                          "scrollable-vertical": false, 
                          "adapter-view": false, 
                          "abs-pos": true, 
                          "pointer": "afb92d2", 
                          "class": "android.widget.TextView", 
                          "visible-to-user": true
                        }, 
                        {
                          "resource-id": "com.kauf.sticker.funfacechangerproeffects:id/LinearLayoutStickerTextFonttype", 
                          "adapter-view": false, 
                          "pointer": "445afa3", 
                          "children": [
                            {
                              "scrollable-horizontal": false, 
                              "draw": true, 
                              "ancestors": [
                                "android.widget.LinearLayout", 
                                "android.view.ViewGroup", 
                                "android.view.View", 
                                "java.lang.Object"
                              ], 
                              "clickable": false, 
                              "pressed": "not_pressed", 
                              "focusable": false, 
                              "long-clickable": false, 
                              "enabled": true, 
                              "bounds": [
                                18, 
                                1661, 
                                1422, 
                                2135
                              ], 
                              "visibility": "visible", 
                              "content-desc": [
                                null
                              ], 
                              "rel-bounds": [
                                0, 
                                0, 
                                1404, 
                                474
                              ], 
                              "focused": false, 
                              "selected": false, 
                              "scrollable-vertical": false, 
                              "children": [
                                {
                                  "text": "Intuitive", 
                                  "scrollable-vertical": false, 
                                  "adapter-view": false, 
                                  "pointer": "b3f2e59", 
                                  "scrollable-horizontal": false, 
                                  "ancestors": [
                                    "android.widget.CompoundButton", 
                                    "android.widget.Button", 
                                    "android.widget.TextView", 
                                    "android.view.View", 
                                    "java.lang.Object"
                                  ], 
                                  "selected": false, 
                                  "content-desc": [
                                    null
                                  ], 
                                  "rel-bounds": [
                                    0, 
                                    0, 
                                    1404, 
                                    112
                                  ], 
                                  "draw": false, 
                                  "focusable": true, 
                                  "long-clickable": false, 
                                  "visibility": "visible", 
                                  "focused": false, 
                                  "clickable": true, 
                                  "abs-pos": true, 
                                  "font-family": "default", 
                                  "class": "android.widget.RadioButton", 
                                  "visible-to-user": true, 
                                  "enabled": true, 
                                  "bounds": [
                                    18, 
                                    1661, 
                                    1422, 
                                    1773
                                  ], 
                                  "pressed": "not_pressed"
                                }, 
                                {
                                  "text": "Modern Antiqua", 
                                  "scrollable-vertical": false, 
                                  "adapter-view": false, 
                                  "pointer": "bdc0a1e", 
                                  "scrollable-horizontal": false, 
                                  "ancestors": [
                                    "android.widget.CompoundButton", 
                                    "android.widget.Button", 
                                    "android.widget.TextView", 
                                    "android.view.View", 
                                    "java.lang.Object"
                                  ], 
                                  "selected": false, 
                                  "content-desc": [
                                    null
                                  ], 
                                  "rel-bounds": [
                                    0, 
                                    112, 
                                    1404, 
                                    224
                                  ], 
                                  "draw": false, 
                                  "focusable": true, 
                                  "long-clickable": false, 
                                  "visibility": "visible", 
                                  "focused": false, 
                                  "clickable": true, 
                                  "abs-pos": true, 
                                  "font-family": "default", 
                                  "class": "android.widget.RadioButton", 
                                  "visible-to-user": true, 
                                  "enabled": true, 
                                  "bounds": [
                                    18, 
                                    1773, 
                                    1422, 
                                    1885
                                  ], 
                                  "pressed": "not_pressed"
                                }, 
                                {
                                  "text": "Pfennig", 
                                  "scrollable-vertical": false, 
                                  "adapter-view": false, 
                                  "pointer": "8f9a2ff", 
                                  "scrollable-horizontal": false, 
                                  "ancestors": [
                                    "android.widget.CompoundButton", 
                                    "android.widget.Button", 
                                    "android.widget.TextView", 
                                    "android.view.View", 
                                    "java.lang.Object"
                                  ], 
                                  "selected": false, 
                                  "content-desc": [
                                    null
                                  ], 
                                  "rel-bounds": [
                                    0, 
                                    224, 
                                    1404, 
                                    336
                                  ], 
                                  "draw": false, 
                                  "focusable": true, 
                                  "long-clickable": false, 
                                  "visibility": "visible", 
                                  "focused": false, 
                                  "clickable": true, 
                                  "abs-pos": true, 
                                  "font-family": "default", 
                                  "class": "android.widget.RadioButton", 
                                  "visible-to-user": true, 
                                  "enabled": true, 
                                  "bounds": [
                                    18, 
                                    1885, 
                                    1422, 
                                    1997
                                  ], 
                                  "pressed": "not_pressed"
                                }, 
                                {
                                  "text": "Puntillas", 
                                  "scrollable-vertical": false, 
                                  "adapter-view": false, 
                                  "pointer": "22e48cc", 
                                  "scrollable-horizontal": false, 
                                  "ancestors": [
                                    "android.widget.CompoundButton", 
                                    "android.widget.Button", 
                                    "android.widget.TextView", 
                                    "android.view.View", 
                                    "java.lang.Object"
                                  ], 
                                  "selected": false, 
                                  "content-desc": [
                                    null
                                  ], 
                                  "rel-bounds": [
                                    0, 
                                    336, 
                                    1404, 
                                    474
                                  ], 
                                  "draw": false, 
                                  "focusable": true, 
                                  "long-clickable": false, 
                                  "visibility": "visible", 
                                  "focused": false, 
                                  "clickable": true, 
                                  "abs-pos": true, 
                                  "font-family": "default", 
                                  "class": "android.widget.RadioButton", 
                                  "visible-to-user": true, 
                                  "enabled": true, 
                                  "bounds": [
                                    18, 
                                    1997, 
                                    1422, 
                                    2135
                                  ], 
                                  "pressed": "not_pressed"
                                }
                              ], 
                              "adapter-view": false, 
                              "abs-pos": true, 
                              "pointer": "841a2a0", 
                              "class": "android.widget.RadioGroup", 
                              "visible-to-user": true
                            }
                          ], 
                          "scrollable-horizontal": false, 
                          "ancestors": [
                            "android.view.ViewGroup", 
                            "android.view.View", 
                            "java.lang.Object"
                          ], 
                          "selected": false, 
                          "content-desc": [
                            null
                          ], 
                          "rel-bounds": [
                            18, 
                            1661, 
                            1422, 
                            2135
                          ], 
                          "draw": true, 
                          "focusable": false, 
                          "long-clickable": false, 
                          "visibility": "visible", 
                          "focused": false, 
                          "clickable": false, 
                          "abs-pos": true, 
                          "class": "android.widget.LinearLayout", 
                          "visible-to-user": true, 
                          "package": "com.kauf.sticker.funfacechangerproeffects", 
                          "enabled": true, 
                          "bounds": [
                            18, 
                            1661, 
                            1422, 
                            2135
                          ], 
                          "pressed": "not_pressed", 
                          "scrollable-vertical": false
                        }, 
                        {
                          "text": "Create text", 
                          "resource-id": "com.kauf.sticker.funfacechangerproeffects:id/ButtonStickerTextCreate", 
                          "adapter-view": false, 
                          "pointer": "1ab5715", 
                          "scrollable-horizontal": false, 
                          "ancestors": [
                            "android.widget.TextView", 
                            "android.view.View", 
                            "java.lang.Object"
                          ], 
                          "selected": false, 
                          "content-desc": [
                            null
                          ], 
                          "rel-bounds": [
                            18, 
                            2205, 
                            1422, 
                            2373
                          ], 
                          "draw": false, 
                          "focusable": true, 
                          "long-clickable": false, 
                          "visibility": "visible", 
                          "focused": false, 
                          "clickable": true, 
                          "abs-pos": true, 
                          "class": "android.widget.Button", 
                          "visible-to-user": true, 
                          "package": "com.kauf.sticker.funfacechangerproeffects", 
                          "enabled": true, 
                          "bounds": [
                            18, 
                            2205, 
                            1422, 
                            2373
                          ], 
                          "pressed": "not_pressed", 
                          "scrollable-vertical": false
                        }
                      ], 
                      "adapter-view": false, 
                      "abs-pos": true, 
                      "pointer": "c71291f", 
                      "class": "android.widget.LinearLayout", 
                      "visible-to-user": true
                    }
                  ], 
                  "adapter-view": false, 
                  "abs-pos": true, 
                  "pointer": "f4354be", 
                  "class": "android.widget.ScrollView", 
                  "visible-to-user": true
                }
              ], 
              "scrollable-horizontal": false, 
              "ancestors": [
                "android.view.ViewGroup", 
                "android.view.View", 
                "java.lang.Object"
              ], 
              "selected": false, 
              "content-desc": [
                null
              ], 
              "rel-bounds": [
                0, 
                0, 
                1440, 
                2392
              ], 
              "draw": true, 
              "focusable": false, 
              "long-clickable": false, 
              "visibility": "visible", 
              "focused": false, 
              "clickable": false, 
              "abs-pos": true, 
              "class": "android.widget.FrameLayout", 
              "visible-to-user": true, 
              "package": "android", 
              "enabled": true, 
              "bounds": [
                0, 
                0, 
                1440, 
                2392
              ], 
              "pressed": "not_pressed", 
              "scrollable-vertical": false
            }
          ], 
          "adapter-view": false, 
          "abs-pos": true, 
          "pointer": "6fb13c3", 
          "class": "android.widget.LinearLayout", 
          "visible-to-user": true
        }
      ], 
      "adapter-view": false, 
      "abs-pos": true, 
      "pointer": "a957372", 
      "class": "com.android.internal.policy.PhoneWindow$DecorView", 
      "visible-to-user": true
    }, 
    "added_fragments": [], 
    "active_fragments": []
  }, 
  "is_keyboard_deployed": false, 
  "request_id": "330"
}